wbin
